corva_otel/autoinstrumentation/__init__.py
corva_otel/autoinstrumentation/initialize.py
corva_otel/autoinstrumentation/logging_extensions.py
corva_otel/autoinstrumentation/requests_extensions.py
corva_otel/autoinstrumentation/urllib3_sockets.py
corva_otel_autoinstrumentation-0.4.0.dist-info/METADATA
corva_otel_autoinstrumentation-0.4.0.dist-info/WHEEL
corva_otel_autoinstrumentation-0.4.0.dist-info/RECORD
